pacssim/FunctionInstance.py
pacssim/ServerlessSimulator.py
pacssim/ServerlessTemporalSimulator.py
pacssim/SimProcess.py
pacssim/Utility.py
pacssim/__init__.py
pacssim-0.1.4.dist-info/LICENSE
pacssim-0.1.4.dist-info/METADATA
pacssim-0.1.4.dist-info/WHEEL
pacssim-0.1.4.dist-info/top_level.txt
pacssim-0.1.4.dist-info/RECORD
